sparklehorse/__init__.py
sparklehorse/marklinkous/ChestFullOfDyingHawks.py
sparklehorse/marklinkous/ChordsIveKnown.py
sparklehorse/marklinkous/DistortedGhostEP.py
sparklehorse/marklinkous/DontTakeMySunshineAway.py
sparklehorse/marklinkous/DreamtForLightYearsInTheBellyOfAMountain.py
sparklehorse/marklinkous/GoldDay.py
sparklehorse/marklinkous/GoodMorningSpider.py
sparklehorse/marklinkous/HammeringTheCramps_SpiritDitch.py
sparklehorse/marklinkous/IntheFishtank15.py
sparklehorse/marklinkous/ItsAWonderfulLife.py
sparklehorse/marklinkous/KnivesOfSummertime.py
sparklehorse/marklinkous/London.py
sparklehorse/marklinkous/MariasLittleElbows.py
sparklehorse/marklinkous/Rainmaker.py
sparklehorse/marklinkous/Rainmaker2.py
sparklehorse/marklinkous/SickOfGoodbyes.py
sparklehorse/marklinkous/SomedayIWillTreatYouGood.py
sparklehorse/marklinkous/Vivadixiesubmarinetransmissionplot.py
sparklehorse/marklinkous/__init__.py
sparklehorse-0.1.3.dist-info/METADATA
sparklehorse-0.1.3.dist-info/WHEEL
sparklehorse-0.1.3.dist-info/top_level.txt
sparklehorse-0.1.3.dist-info/RECORD
