Metadata-Version: 2.1
Name: sparklehorse
Version: 0.1.3
Summary: just 4 remember.
Home-page: UNKNOWN
Author: vilame
Author-email: opaquism@hotmail.com
License: MIT
Keywords: sparklehorse
Platform: UNKNOWN
Classifier: License :: OSI Approved :: MIT License
Classifier: Programming Language :: Python
Classifier: Intended Audience :: Developers
